al_dag_kits/__init__.py
al_dag_kits/common_utils/__init__.py
al_dag_kits/common_utils/v1/__init__.py
al_dag_kits/common_utils/v1/al_team_tag.py
al_dag_kits/common_utils/v1/helper.py
al_dag_kits/common_utils/v1/slack_utils.py
al_dag_kits/spark_utils/__init__.py
al_dag_kits/spark_utils/v1/__init__.py
al_dag_kits/spark_utils/v1/k8s/__init__.py
al_dag_kits/spark_utils/v1/k8s/al_cluster_tolerations.py
al_dag_kits/spark_utils/v1/k8s/al_custom_object_launcher.py
al_dag_kits/spark_utils/v1/k8s/al_kubernetes_pod_trigger.py
al_dag_kits/spark_utils/v1/k8s/al_kubernetes_pod_trigger_debug.py
al_dag_kits/spark_utils/v1/k8s/al_spark_kubernetes.py
al_dag_kits/spark_utils/v1/k8s/al_spark_kubernetes_debug.py
al_dag_kits/spark_utils/v1/k8s/spark_application_spec.py
al_dag_kits/spark_utils/v1/k8s/spark_application_spec_builder.py
al_dag_kits-1.4.3.dist-info/METADATA
al_dag_kits-1.4.3.dist-info/WHEEL
al_dag_kits-1.4.3.dist-info/top_level.txt
al_dag_kits-1.4.3.dist-info/RECORD
